claire_organizer/__init__.py
claire_organizer/main.py
claire_organizer-2.0.0.dist-info/LICENSE
claire_organizer-2.0.0.dist-info/METADATA
claire_organizer-2.0.0.dist-info/WHEEL
claire_organizer-2.0.0.dist-info/entry_points.txt
claire_organizer-2.0.0.dist-info/top_level.txt
claire_organizer-2.0.0.dist-info/RECORD
