Metadata-Version: 2.2
Name: claire_organizer
Version: 2.0.0
Summary: A command line file organizer made. My largest project so far.
Home-page: https://github.com/uwungu01-rep/claire_organizer-python.edition
Author: Zizel
Author-email: danbua999@gmail.com
Classifier: Programming Language :: Python :: 3
Classifier: Operating System :: OS Independent
Classifier: License :: OSI Approved :: GNU General Public License v3 (GPLv3)
License-File: LICENSE
Requires-Dist: ziz_utils
Dynamic: author
Dynamic: author-email
Dynamic: classifier
Dynamic: description
Dynamic: description-content-type
Dynamic: home-page
Dynamic: requires-dist
Dynamic: summary
